{"name":"Canadian Crewmates","division":"Australis","color1":"#D7E1F1","color2":"#C01A17","roster":[{"name":"Phroodles#1533","draft":"0","tank":"2878","damage":"2862","support":"2751"},{"name":"FedoraMaster#11895","draft":"5","tank":"3528","damage":"3665","support":"3420"},{"name":"wigglehiggle#1304","draft":"20","tank":"-","damage":"-","support":"2087"},{"name":"Nyamonya#1846","draft":"29","tank":"-","damage":"-","support":"3509"},{"name":"Vind#11245","draft":"44","tank":"3850","damage":"-","support":"3457"},{"name":"kirbology#1130","draft":"53","tank":"-","damage":"-","support":"2767"}],"maps":[{"mapname":"Lijiang Tower","wins":"1","losses":"0","draws":"0","winrate":"100.0%"},{"mapname":"Busan","wins":"0","losses":"0","draws":"0","winrate":"0.0%"},{"mapname":"Ilios","wins":"0","losses":"1","draws":"0","winrate":"0.0%"},{"mapname":"Nepal","wins":"0","losses":"0","draws":"0","winrate":"0.0%"},{"mapname":"Oasis","wins":"0","losses":"0","draws":"0","winrate":"0.0%"},{"mapname":"King&apos;s Row","wins":"2","losses":"2","draws":"0","winrate":"50.0%"},{"mapname":"Eichenwalde","wins":"0","losses":"0","draws":"0","winrate":"0.0%"},{"mapname":"Hollywood","wins":"0","losses":"0","draws":"0","winrate":"0.0%"},{"mapname":"Numbani","wins":"1","losses":"0","draws":"0","winrate":"100.0%"},{"mapname":"Blizzard World","wins":"0","losses":"0","draws":"0","winrate":"0.0%"},{"mapname":"Dorado","wins":"0","losses":"0","draws":"0","winrate":"0.0%"},{"mapname":"Havana","wins":"0","losses":"0","draws":"0","winrate":"0.0%"},{"mapname":"Route: 66","wins":"1","losses":"1","draws":"0","winrate":"50.0%"},{"mapname":"Junkertown","wins":"0","losses":"1","draws":"0","winrate":"0.0%"},{"mapname":"Rialto","wins":"1","losses":"0","draws":"0","winrate":"100.0%"},{"mapname":"Watchpoint: Gibraltar","wins":"0","losses":"0","draws":"0","winrate":"0.0%"},{"mapname":"Colosseo","wins":"0","losses":"0","draws":"0","winrate":"0.0%"},{"mapname":"New Queen Street","wins":"0","losses":"0","draws":"0","winrate":"0.0%"},{"mapname":"Esperanca","wins":"0","losses":"0","draws":"0","winrate":"0.0%"}],"matches":[{"tournament":"Season","opponent":"Mankato Mammoths","date":"10/21/2022","time":"8:00:00 PM","played":"TRUE","map1":{"name":"New Queen Street","winner":"Mankato Mammoths"},"map2":{"name":"King&apos;s Row","winner":"Canadian Crewmates"},"map3":{"name":"Route: 66","winner":"Canadian Crewmates"},"map4":{"name":"Nepal","winner":"Canadian Crewmates"},"map5":{"name":"","winner":""},"map6":{"name":"","winner":""},"map7":{"name":"","winner":""},"map8":{"name":"","winner":""},"winner":"Canadian Crewmates","division":"DIV","vod":"","round":"1"},{"tournament":"Season","opponent":"Casablancan Cappy Blappies","date":"10/29/2022","time":"7:00:00 PM","played":"TRUE","map1":{"name":"Ilios","winner":"Casablancan Cappy Blappies"},"map2":{"name":"King&apos;s Row","winner":"Casablancan Cappy Blappies"},"map3":{"name":"Route: 66","winner":"Casablancan Cappy Blappies"},"map4":{"name":"","winner":""},"map5":{"name":"","winner":""},"map6":{"name":"","winner":""},"map7":{"name":"","winner":""},"map8":{"name":"","winner":""},"winner":"Casablancan Cappy Blappies","division":"DIV","vod":"","round":"2"},{"tournament":"Season","opponent":"Handsome Hogs","date":"11/5/2022","time":"8:00:00 PM","played":"TRUE","map1":{"name":"Colosseo","winner":"Handsome Hogs"},"map2":{"name":"King&apos;s Row","winner":"Handsome Hogs"},"map3":{"name":"Junkertown","winner":"Handsome Hogs"},"map4":{"name":"","winner":""},"map5":{"name":"","winner":""},"map6":{"name":"","winner":""},"map7":{"name":"","winner":""},"map8":{"name":"","winner":""},"winner":"Handsome Hogs","division":"DIV","vod":"","round":"3"},{"tournament":"Season","opponent":"New York City Newts","date":"11/11/2022","time":"8:00:00 PM","played":"TRUE","map1":{"name":"Lijiang Tower","winner":"Canadian Crewmates"},"map2":{"name":"Numbani","winner":"Canadian Crewmates"},"map3":{"name":"Rialto","winner":"Canadian Crewmates"},"map4":{"name":"","winner":""},"map5":{"name":"","winner":""},"map6":{"name":"","winner":""},"map7":{"name":"","winner":""},"map8":{"name":"","winner":""},"winner":"Canadian Crewmates","division":"DIV","vod":"","round":"4"},{"tournament":"Season","opponent":"Brooklyn Bricks","date":"11/21/2022","time":"8:00:00 PM","played":"TRUE","map1":{"name":"Esperanca","winner":"Canadian Crewmates"},"map2":{"name":"King&apos;s Row","winner":"Canadian Crewmates"},"map3":{"name":"Circuit Royale","winner":"Canadian Crewmates"},"map4":{"name":"","winner":""},"map5":{"name":"","winner":""},"map6":{"name":"","winner":""},"map7":{"name":"","winner":""},"map8":{"name":"","winner":""},"winner":"Canadian Crewmates","division":"DIV","vod":"","round":"5"}],"stats":{"All":{"wins":"3","losses":"2","mapwins":"6","maplosses":"5","mapties":"0","mapdiff":"1","rank":"6/12"},"Season":{"wins":"3","losses":"2","mapwins":"9","maplosses":"7","mapties":"0","mapdiff":"2","rank":"0"},"Postseason":{"wins":"0","losses":"0","mapwins":"0","maplosses":"0","mapties":"0","mapdiff":"0","rank":"0"}}}