{
	"League Stats" : "All",
	"Ana" : "Support",
	"Ashe" : "Damage",
	"Baptiste" : "Support",
	"Bastion" : "Damage",
	"Brigitte" : "Support",
	"D.Va" : "Tank",
	"Doomfist" : "Damage",
	"Echo" : "Damage",
	"Genji" : "Damage",
	"Hanzo" : "Damage",
	"Junkrat" : "Damage",
	"Lucio" : "Support",
	"McCree" : "Damage",
	"Mei" : "Damage",
	"Mercy" : "Support",
	"Moira" : "Support",
	"Orisa" : "Tank",
	"Pharah" : "Damage",
	"Reaper" : "Damage",
	"Reinhardt" : "Tank",
	"Roadhog" : "Tank",
	"Sigma" : "Tank",
	"Soldier: 76" : "Damage",
	"Sombra" : "Damage",
	"Symmetra" : "Damage",
	"Torbjorn" : "Damage",
	"Tracer" : "Damage",
	"Widowmaker" : "Damage",
	"Wrecking Ball" : "Tank",
	"Zarya" : "Tank",
	"Zenyatta" : "Support"
}