{"updated":"24-07-2021 15:09:30","currentround":5,"matches":[{"tournament":"Tourn 1","played":"TRUE","team1":"Oceania Otters","team2":"Bendigo Bilbies","division":"NDIV","date":"6/10/2021","time":"7:00:00 PM","map1":{"name":"Busan","winner":"Bendigo Bilbies"},"map2":{"name":"King's Row","winner":"Bendigo Bilbies"},"map3":{"name":"Rialto","winner":"Bendigo Bilbies"},"map4":{"name":"","winner":""},"map5":{"name":"","winner":""},"map6":{"name":"","winner":""},"map7":{"name":"","winner":""},"map8":{"name":"","winner":""},"matchwinner":"Bendigo Bilbies","vod":"https://www.twitch.tv/videos/1052358421","round":"1"},{"tournament":"Tourn 1","played":"TRUE","team1":"Plymouth PMAs","team2":"Djibouti Shorts","division":"DIV","date":"6/6/2021","time":"9:00:00 PM","map1":{"name":"Busan","winner":"Plymouth PMAs"},"map2":{"name":"King's Row","winner":"Djibouti Shorts"},"map3":{"name":"Rialto","winner":"Plymouth PMAs"},"map4":{"name":"Volskaya Industries","winner":"Draw"},"map5":{"name":"Lijiang Tower","winner":"Djibouti Shorts"},"map6":{"name":"Oasis","winner":"Plymouth PMAs"},"map7":{"name":"","winner":""},"map8":{"name":"","winner":""},"matchwinner":"Plymouth PMAs","vod":"","round":"1"},{"tournament":"Tourn 1","played":"TRUE","team1":"Galapagos Gremlins","team2":"Gaming Golems","division":"DIV","date":"5/31/2021","time":"8:00:00 PM","map1":{"name":"Busan","winner":"Galapagos Gremlins"},"map2":{"name":"Numbani","winner":"Galapagos Gremlins"},"map3":{"name":"Watchpoint: Gibraltar","winner":"Galapagos Gremlins"},"map4":{"name":"","winner":""},"map5":{"name":"","winner":""},"map6":{"name":"","winner":""},"map7":{"name":"","winner":""},"map8":{"name":"","winner":""},"matchwinner":"Galapagos Gremlins","vod":"https://www.youtube.com/watch?v=yN2fggGp3Qk","round":"1"},{"tournament":"Tourn 1","played":"TRUE","team1":"Wakanda BBQs","team2":"The Tenochitlan Tacos","division":"NDIV","date":"6/2/2021","time":"7:00:00 PM","map1":{"name":"Busan","winner":"The Tenochitlan Tacos"},"map2":{"name":"King's Row","winner":"Wakanda BBQs"},"map3":{"name":"Watchpoint: Gibraltar","winner":"Wakanda BBQs"},"map4":{"name":"Temple of Anubis","winner":"Wakanda BBQs"},"map5":{"name":"","winner":""},"map6":{"name":"","winner":""},"map7":{"name":"","winner":""},"map8":{"name":"","winner":""},"matchwinner":"Wakanda BBQs","vod":"https://youtu.be/DZk56BsnhhE","round":"1"},{"tournament":"Tourn 1","played":"TRUE","team1":"London Lumberjack Slams","team2":"Rialto Rincewinds","division":"NDIV","date":"6/8/2021","time":"7:00:00 PM","map1":{"name":"Busan","winner":"Rialto Rincewinds"},"map2":{"name":"King's Row","winner":"London Lumberjack Slams"},"map3":{"name":"Route: 66","winner":"London Lumberjack Slams"},"map4":{"name":"Hanamura","winner":"Rialto Rincewinds"},"map5":{"name":"Lijiang Tower","winner":"London Lumberjack Slams"},"map6":{"name":"","winner":""},"map7":{"name":"","winner":""},"map8":{"name":"","winner":""},"matchwinner":"London Lumberjack Slams","vod":"https://www.youtube.com/watch?v=nPRmqVQ74w0","round":"1"},{"tournament":"Tourn 1","played":"TRUE","team1":"Oceania Otters","team2":"Galapagos Gremlins","division":"NDIV","date":"6/14/2021","time":"8:00:00 PM","map1":{"name":"Busan","winner":"Oceania Otters"},"map2":{"name":"Numbani","winner":"Galapagos Gremlins"},"map3":{"name":"Rialto","winner":"Oceania Otters"},"map4":{"name":"Volskaya Industries","winner":"Galapagos Gremlins"},"map5":{"name":"Lijiang Tower","winner":"Galapagos Gremlins"},"map6":{"name":"","winner":""},"map7":{"name":"","winner":""},"map8":{"name":"","winner":""},"matchwinner":"Galapagos Gremlins","vod":"","round":"2"},{"tournament":"Tourn 1","played":"TRUE","team1":"London Lumberjack Slams","team2":"Bendigo Bilbies","division":"NDIV","date":"6/17/2021","time":"7:30:00 PM","map1":{"name":"Busan","winner":"London Lumberjack Slams"},"map2":{"name":"Hollywood","winner":"London Lumberjack Slams"},"map3":{"name":"Junkertown","winner":"London Lumberjack Slams"},"map4":{"name":"","winner":""},"map5":{"name":"","winner":""},"map6":{"name":"","winner":""},"map7":{"name":"","winner":""},"map8":{"name":"","winner":""},"matchwinner":"London Lumberjack Slams","vod":"https://www.twitch.tv/videos/1059560560","round":"2"},{"tournament":"Tourn 1","played":"TRUE","team1":"Plymouth PMAs","team2":"Gaming Golems","division":"NDIV","date":"6/13/2021","time":"7:00:00 PM","map1":{"name":"Busan","winner":"Plymouth PMAs"},"map2":{"name":"King's Row","winner":"Gaming Golems"},"map3":{"name":"Rialto","winner":"Gaming Golems"},"map4":{"name":"Numbani","winner":"Plymouth PMAs"},"map5":{"name":"Nepal","winner":"Gaming Golems"},"map6":{"name":"","winner":""},"map7":{"name":"","winner":""},"map8":{"name":"","winner":""},"matchwinner":"Gaming Golems","vod":"https://youtu.be/leD_nLTUTjI","round":"2"},{"tournament":"Tourn 1","played":"TRUE","team1":"Wakanda BBQs","team2":"Rialto Rincewinds","division":"DIV","date":"6/15/2021","time":"8:00:00 PM","map1":{"name":"Busan","winner":"Rialto Rincewinds"},"map2":{"name":"King's Row","winner":"Wakanda BBQs"},"map3":{"name":"Route: 66","winner":"Rialto Rincewinds"},"map4":{"name":"Temple of Anubis","winner":"Wakanda BBQs"},"map5":{"name":"Ilios","winner":"Wakanda BBQs"},"map6":{"name":"","winner":""},"map7":{"name":"","winner":""},"map8":{"name":"","winner":""},"matchwinner":"Wakanda BBQs","vod":"https://www.twitch.tv/videos/1057549608","round":"2"},{"tournament":"Tourn 1","played":"TRUE","team1":"The Tenochitlan Tacos","team2":"Djibouti Shorts","division":"DIV","date":"6/20/2021","time":"9:00:00 PM","map1":{"name":"Busan","winner":"Djibouti Shorts"},"map2":{"name":"Numbani","winner":"The Tenochitlan Tacos"},"map3":{"name":"Rialto","winner":"Djibouti Shorts"},"map4":{"name":"Volskaya Industries","winner":"The Tenochitlan Tacos"},"map5":{"name":"Lijiang Tower","winner":"The Tenochitlan Tacos"},"map6":{"name":"","winner":""},"map7":{"name":"","winner":""},"map8":{"name":"","winner":""},"matchwinner":"The Tenochitlan Tacos","vod":"https://www.twitch.tv/videos/1062668365","round":"2"},{"tournament":"Tourn 1","played":"TRUE","team1":"Oceania Otters","team2":"London Lumberjack Slams","division":"DIV","date":"6/24/2021","time":"7:00:00 PM","map1":{"name":"Busan","winner":"Oceania Otters"},"map2":{"name":"King's Row","winner":"London Lumberjack Slams"},"map3":{"name":"Havana","winner":"Oceania Otters"},"map4":{"name":"Blizzard World","winner":"London Lumberjack Slams"},"map5":{"name":"Lijiang Tower","winner":"Oceania Otters"},"map6":{"name":"","winner":""},"map7":{"name":"","winner":""},"map8":{"name":"","winner":""},"matchwinner":"Oceania Otters","vod":"","round":"3"},{"tournament":"Tourn 1","played":"TRUE","team1":"Plymouth PMAs","team2":"Galapagos Gremlins","division":"NDIV","date":"6/21/2021","time":"8:00:00 PM","map1":{"name":"Busan","winner":"Galapagos Gremlins"},"map2":{"name":"Eichenwalde","winner":"Galapagos Gremlins"},"map3":{"name":"Junkertown","winner":"Galapagos Gremlins"},"map4":{"name":"","winner":""},"map5":{"name":"","winner":""},"map6":{"name":"","winner":""},"map7":{"name":"","winner":""},"map8":{"name":"","winner":""},"matchwinner":"Galapagos Gremlins","vod":"","round":"3"},{"tournament":"Tourn 1","played":"TRUE","team1":"Wakanda BBQs","team2":"Bendigo Bilbies","division":"DIV","date":"6/22/2021","time":"7:00:00 PM","map1":{"name":"Busan","winner":"Bendigo Bilbies"},"map2":{"name":"King's Row","winner":"Bendigo Bilbies"},"map3":{"name":"Route: 66","winner":"Bendigo Bilbies"},"map4":{"name":"","winner":""},"map5":{"name":"","winner":""},"map6":{"name":"","winner":""},"map7":{"name":"","winner":""},"map8":{"name":"","winner":""},"matchwinner":"Bendigo Bilbies","vod":"","round":"3"},{"tournament":"Tourn 1","played":"TRUE","team1":"The Tenochitlan Tacos","team2":"Gaming Golems","division":"NDIV","date":"6/23/2021","time":"7:00:00 PM","map1":{"name":"Busan","winner":"Gaming Golems"},"map2":{"name":"King's Row","winner":"The Tenochitlan Tacos"},"map3":{"name":"Rialto","winner":"Gaming Golems"},"map4":{"name":"Volskaya Industries","winner":"Gaming Golems"},"map5":{"name":"","winner":""},"map6":{"name":"","winner":""},"map7":{"name":"","winner":""},"map8":{"name":"","winner":""},"matchwinner":"Gaming Golems","vod":"","round":"3"},{"tournament":"Tourn 1","played":"TRUE","team1":"Djibouti Shorts","team2":"Rialto Rincewinds","division":"NDIV","date":"6/27/2021","time":"7:00:00 PM","map1":{"name":"Busan","winner":"Rialto Rincewinds"},"map2":{"name":"King's Row","winner":"Rialto Rincewinds"},"map3":{"name":"Junkertown","winner":"Rialto Rincewinds"},"map4":{"name":"","winner":""},"map5":{"name":"","winner":""},"map6":{"name":"","winner":""},"map7":{"name":"","winner":""},"map8":{"name":"","winner":""},"matchwinner":"Rialto Rincewinds","vod":"","round":"3"},{"tournament":"Tourn 1 playins","played":"FALSE","team1":"","team2":"","division":"","date":"","time":"","map1":{"name":"undefined","winner":"undefined"},"map2":{"name":"undefined","winner":"undefined"},"map3":{"name":"undefined","winner":"undefined"},"map4":{"name":"undefined","winner":"undefined"},"map5":{"name":"undefined","winner":"undefined"},"map6":{"name":"undefined","winner":"undefined"},"map7":{"name":"undefined","winner":"undefined"},"map8":{"name":"undefined","winner":"undefined"},"matchwinner":"undefined","vod":"undefined","round":"undefined"},{"tournament":"Tourn 1 playins","played":"FALSE","team1":"","team2":"","division":"","date":"","time":"","map1":{"name":"undefined","winner":"undefined"},"map2":{"name":"undefined","winner":"undefined"},"map3":{"name":"undefined","winner":"undefined"},"map4":{"name":"undefined","winner":"undefined"},"map5":{"name":"undefined","winner":"undefined"},"map6":{"name":"undefined","winner":"undefined"},"map7":{"name":"undefined","winner":"undefined"},"map8":{"name":"undefined","winner":"undefined"},"matchwinner":"undefined","vod":"undefined","round":"undefined"},{"tournament":"Tourn 1 playins","played":"FALSE","team1":"","team2":"","division":"","date":"","time":"","map1":{"name":"undefined","winner":"undefined"},"map2":{"name":"undefined","winner":"undefined"},"map3":{"name":"undefined","winner":"undefined"},"map4":{"name":"undefined","winner":"undefined"},"map5":{"name":"undefined","winner":"undefined"},"map6":{"name":"undefined","winner":"undefined"},"map7":{"name":"undefined","winner":"undefined"},"map8":{"name":"undefined","winner":"undefined"},"matchwinner":"undefined","vod":"undefined","round":"undefined"},{"tournament":"Tourn 1 playoffs","played":"FALSE","team1":"","team2":"","division":"","date":"","time":"","map1":{"name":"undefined","winner":"undefined"},"map2":{"name":"undefined","winner":"undefined"},"map3":{"name":"undefined","winner":"undefined"},"map4":{"name":"undefined","winner":"undefined"},"map5":{"name":"undefined","winner":"undefined"},"map6":{"name":"undefined","winner":"undefined"},"map7":{"name":"undefined","winner":"undefined"},"map8":{"name":"undefined","winner":"undefined"},"matchwinner":"undefined","vod":"undefined","round":"undefined"},{"tournament":"Tourn 1 playoffs","played":"FALSE","team1":"","team2":"","division":"","date":"","time":"","map1":{"name":"undefined","winner":"undefined"},"map2":{"name":"undefined","winner":"undefined"},"map3":{"name":"undefined","winner":"undefined"},"map4":{"name":"undefined","winner":"undefined"},"map5":{"name":"undefined","winner":"undefined"},"map6":{"name":"undefined","winner":"undefined"},"map7":{"name":"undefined","winner":"undefined"},"map8":{"name":"undefined","winner":"undefined"},"matchwinner":"undefined","vod":"undefined","round":"undefined"},{"tournament":"Tourn 1 playoffs","played":"FALSE","team1":"","team2":"","division":"","date":"","time":"","map1":{"name":"undefined","winner":"undefined"},"map2":{"name":"undefined","winner":"undefined"},"map3":{"name":"undefined","winner":"undefined"},"map4":{"name":"undefined","winner":"undefined"},"map5":{"name":"undefined","winner":"undefined"},"map6":{"name":"undefined","winner":"undefined"},"map7":{"name":"undefined","winner":"undefined"},"map8":{"name":"undefined","winner":"undefined"},"matchwinner":"undefined","vod":"undefined","round":"undefined"},{"tournament":"Tourn 1 playoffs","played":"FALSE","team1":"","team2":"","division":"","date":"","time":"","map1":{"name":"undefined","winner":"undefined"},"map2":{"name":"undefined","winner":"undefined"},"map3":{"name":"undefined","winner":"undefined"},"map4":{"name":"undefined","winner":"undefined"},"map5":{"name":"undefined","winner":"undefined"},"map6":{"name":"undefined","winner":"undefined"},"map7":{"name":"undefined","winner":"undefined"},"map8":{"name":"undefined","winner":"undefined"},"matchwinner":"undefined","vod":"undefined","round":"undefined"},{"tournament":"Tourn 1 playoffs","played":"FALSE","team1":"","team2":"","division":"","date":"","time":"","map1":{"name":"undefined","winner":"undefined"},"map2":{"name":"undefined","winner":"undefined"},"map3":{"name":"undefined","winner":"undefined"},"map4":{"name":"undefined","winner":"undefined"},"map5":{"name":"undefined","winner":"undefined"},"map6":{"name":"undefined","winner":"undefined"},"map7":{"name":"undefined","winner":"undefined"},"map8":{"name":"undefined","winner":"undefined"},"matchwinner":"undefined","vod":"undefined","round":"undefined"},{"tournament":"Tourn 1 playoffs","played":"FALSE","team1":"","team2":"","division":"","date":"","time":"","map1":{"name":"undefined","winner":"undefined"},"map2":{"name":"undefined","winner":"undefined"},"map3":{"name":"undefined","winner":"undefined"},"map4":{"name":"undefined","winner":"undefined"},"map5":{"name":"undefined","winner":"undefined"},"map6":{"name":"undefined","winner":"undefined"},"map7":{"name":"undefined","winner":"undefined"},"map8":{"name":"undefined","winner":"undefined"},"matchwinner":"undefined","vod":"undefined","round":"undefined"},{"tournament":"Tourn 1 playoffs","played":"FALSE","team1":"","team2":"","division":"","date":"","time":"","map1":{"name":"undefined","winner":"undefined"},"map2":{"name":"undefined","winner":"undefined"},"map3":{"name":"undefined","winner":"undefined"},"map4":{"name":"undefined","winner":"undefined"},"map5":{"name":"undefined","winner":"undefined"},"map6":{"name":"undefined","winner":"undefined"},"map7":{"name":"undefined","winner":"undefined"},"map8":{"name":"undefined","winner":"undefined"},"matchwinner":"undefined","vod":"undefined","round":"undefined"},{"tournament":"Tourn 2","played":"TRUE","team1":"Oceania Otters","team2":"Plymouth PMAs","division":"DIV","date":"7/6/2021","time":"8:00 PM","map1":{"name":"Ilios","winner":"Oceania Otters"},"map2":{"name":"King's Row","winner":"Oceania Otters"},"map3":{"name":"Rialto","winner":"Plymouth PMAs"},"map4":{"name":"Hanamura","winner":"Oceania Otters"},"map5":{"name":"","winner":""},"map6":{"name":"","winner":""},"map7":{"name":"","winner":""},"map8":{"name":"","winner":""},"matchwinner":"Oceania Otters","vod":"","round":"4"},{"tournament":"Tourn 2","played":"TRUE","team1":"Wakanda BBQs","team2":"London Lumberjack Slams","division":"NDIV","date":"7/7/2021","time":"7:00:00 PM","map1":{"name":"Ilios","winner":"Wakanda BBQs"},"map2":{"name":"King's Row","winner":"Wakanda BBQs"},"map3":{"name":"Route: 66","winner":"Wakanda BBQs"},"map4":{"name":"","winner":""},"map5":{"name":"","winner":""},"map6":{"name":"","winner":""},"map7":{"name":"","winner":""},"map8":{"name":"","winner":""},"matchwinner":"Wakanda BBQs","vod":"","round":"4"},{"tournament":"Tourn 2","played":"TRUE","team1":"The Tenochitlan Tacos","team2":"Galapagos Gremlins","division":"NDIV","date":"7/8/2021","time":"8:00:00 PM","map1":{"name":"Ilios","winner":"The Tenochitlan Tacos"},"map2":{"name":"King's Row","winner":"The Tenochitlan Tacos"},"map3":{"name":"Watchpoint: Gibraltar","winner":"The Tenochitlan Tacos"},"map4":{"name":"","winner":""},"map5":{"name":"","winner":""},"map6":{"name":"","winner":""},"map7":{"name":"","winner":""},"map8":{"name":"","winner":""},"matchwinner":"The Tenochitlan Tacos","vod":"","round":"4"},{"tournament":"Tourn 2","played":"TRUE","team1":"Djibouti Shorts","team2":"Bendigo Bilbies","division":"NDIV","date":"7/11/2021","time":"7:00:00 PM","map1":{"name":"Ilios","winner":"Djibouti Shorts"},"map2":{"name":"King's Row","winner":"Bendigo Bilbies"},"map3":{"name":"Junkertown","winner":"Bendigo Bilbies"},"map4":{"name":"Eichenwalde","winner":"Djibouti Shorts"},"map5":{"name":"Busan","winner":"Bendigo Bilbies"},"map6":{"name":"","winner":""},"map7":{"name":"","winner":""},"map8":{"name":"","winner":""},"matchwinner":"Bendigo Bilbies","vod":"","round":"4"},{"tournament":"Tourn 2","played":"TRUE","team1":"Rialto Rincewinds","team2":"Gaming Golems","division":"DIV","date":"07/06/2021","time":"7:00:00 PM","map1":{"name":"Ilios","winner":"Gaming Golems"},"map2":{"name":"Numbani","winner":"Rialto Rincewinds"},"map3":{"name":"Rialto","winner":"Rialto Rincewinds"},"map4":{"name":"Hanamura","winner":"Rialto Rincewinds"},"map5":{"name":"","winner":""},"map6":{"name":"","winner":""},"map7":{"name":"","winner":""},"map8":{"name":"","winner":""},"matchwinner":"Rialto Rincewinds","vod":"","round":"4"},{"tournament":"Tourn 2","played":"TRUE","team1":"Oceania Otters","team2":"Wakanda BBQs","division":"NDIV","date":"7/14/2021","time":"8:00:00 PM","map1":{"name":"Ilios","winner":"Oceania Otters"},"map2":{"name":"King's Row","winner":"Oceania Otters"},"map3":{"name":"Junkertown","winner":"Wakanda BBQs"},"map4":{"name":"Hanamura","winner":"Oceania Otters"},"map5":{"name":"","winner":""},"map6":{"name":"","winner":""},"map7":{"name":"","winner":""},"map8":{"name":"","winner":""},"matchwinner":"Oceania Otters","vod":"","round":"5"},{"tournament":"Tourn 2","played":"TRUE","team1":"The Tenochitlan Tacos","team2":"Plymouth PMAs","division":"DIV","date":"7/18/2021","time":"4:00:00 PM","map1":{"name":"Ilios","winner":"The Tenochitlan Tacos"},"map2":{"name":"King's Row","winner":"The Tenochitlan Tacos"},"map3":{"name":"Route: 66","winner":"Plymouth PMAs"},"map4":{"name":"Numbani","winner":"The Tenochitlan Tacos"},"map5":{"name":"","winner":""},"map6":{"name":"","winner":""},"map7":{"name":"","winner":""},"map8":{"name":"","winner":""},"matchwinner":"The Tenochitlan Tacos","vod":"","round":"5"},{"tournament":"Tourn 2","played":"TRUE","team1":"Djibouti Shorts","team2":"London Lumberjack Slams","division":"DIV","date":"7/18/2021","time":"8:00:00 PM","map1":{"name":"Ilios","winner":"Djibouti Shorts"},"map2":{"name":"King's Row","winner":"Djibouti Shorts"},"map3":{"name":"Route: 66","winner":"Djibouti Shorts"},"map4":{"name":"","winner":""},"map5":{"name":"","winner":""},"map6":{"name":"","winner":""},"map7":{"name":"","winner":""},"map8":{"name":"","winner":""},"matchwinner":"Djibouti Shorts","vod":"","round":"5"},{"tournament":"Tourn 2","played":"TRUE","team1":"Rialto Rincewinds","team2":"Galapagos Gremlins","division":"DIV","date":"7/19/2021","time":"8:00:00 PM","map1":{"name":"Ilios","winner":"Galapagos Gremlins"},"map2":{"name":"Numbani","winner":"Rialto Rincewinds"},"map3":{"name":"Junkertown","winner":"Rialto Rincewinds"},"map4":{"name":"Hanamura","winner":"Rialto Rincewinds"},"map5":{"name":"","winner":""},"map6":{"name":"","winner":""},"map7":{"name":"","winner":""},"map8":{"name":"","winner":""},"matchwinner":"Rialto Rincewinds","vod":"","round":"5"},{"tournament":"Tourn 2","played":"TRUE","team1":"Gaming Golems","team2":"Bendigo Bilbies","division":"DIV","date":"7/22/2021","time":"7:00:00 PM","map1":{"name":"Ilios","winner":"Gaming Golems"},"map2":{"name":"King's Row","winner":"Bendigo Bilbies"},"map3":{"name":"Rialto","winner":"Bendigo Bilbies"},"map4":{"name":"Hanamura","winner":"Draw"},"map5":{"name":"Busan","winner":"Bendigo Bilbies"},"map6":{"name":"","winner":""},"map7":{"name":"","winner":""},"map8":{"name":"","winner":""},"matchwinner":"Bendigo Bilbies","vod":"","round":"5"},{"tournament":"Tourn 2","played":"FALSE","team1":"Oceania Otters","team2":"The Tenochitlan Tacos","division":"DIV","date":"","time":"","map1":{"name":"","winner":""},"map2":{"name":"","winner":""},"map3":{"name":"","winner":""},"map4":{"name":"","winner":""},"map5":{"name":"","winner":""},"map6":{"name":"","winner":""},"map7":{"name":"","winner":""},"map8":{"name":"","winner":""},"matchwinner":"","vod":"","round":"6"},{"tournament":"Tourn 2","played":"FALSE","team1":"Djibouti Shorts","team2":"Wakanda BBQs","division":"NDIV","date":"","time":"","map1":{"name":"","winner":""},"map2":{"name":"","winner":""},"map3":{"name":"","winner":""},"map4":{"name":"","winner":""},"map5":{"name":"","winner":""},"map6":{"name":"","winner":""},"map7":{"name":"","winner":""},"map8":{"name":"","winner":""},"matchwinner":"","vod":"","round":"6"},{"tournament":"Tourn 2","played":"FALSE","team1":"Rialto Rincewinds","team2":"Plymouth PMAs","division":"NDIV","date":"7/26/2021","time":"7:00:00 PM","map1":{"name":"","winner":""},"map2":{"name":"","winner":""},"map3":{"name":"","winner":""},"map4":{"name":"","winner":""},"map5":{"name":"","winner":""},"map6":{"name":"","winner":""},"map7":{"name":"","winner":""},"map8":{"name":"","winner":""},"matchwinner":"","vod":"","round":"6"},{"tournament":"Tourn 2","played":"FALSE","team1":"Gaming Golems","team2":"London Lumberjack Slams","division":"NDIV","date":"","time":"","map1":{"name":"","winner":""},"map2":{"name":"","winner":""},"map3":{"name":"","winner":""},"map4":{"name":"","winner":""},"map5":{"name":"","winner":""},"map6":{"name":"","winner":""},"map7":{"name":"","winner":""},"map8":{"name":"","winner":""},"matchwinner":"","vod":"","round":"6"},{"tournament":"Tourn 2","played":"FALSE","team1":"Bendigo Bilbies","team2":"Galapagos Gremlins","division":"DIV","date":"","time":"","map1":{"name":"","winner":""},"map2":{"name":"","winner":""},"map3":{"name":"","winner":""},"map4":{"name":"","winner":""},"map5":{"name":"","winner":""},"map6":{"name":"","winner":""},"map7":{"name":"","winner":""},"map8":{"name":"","winner":""},"matchwinner":"","vod":"","round":"6"},{"tournament":"Tourn 2 playins","played":"FALSE","team1":"","team2":"","division":"","date":"","time":"","map1":{"name":"undefined","winner":"undefined"},"map2":{"name":"undefined","winner":"undefined"},"map3":{"name":"undefined","winner":"undefined"},"map4":{"name":"undefined","winner":"undefined"},"map5":{"name":"undefined","winner":"undefined"},"map6":{"name":"undefined","winner":"undefined"},"map7":{"name":"undefined","winner":"undefined"},"map8":{"name":"undefined","winner":"undefined"},"matchwinner":"undefined","vod":"undefined","round":"undefined"},{"tournament":"Tourn 2 playins","played":"FALSE","team1":"","team2":"","division":"","date":"","time":"","map1":{"name":"undefined","winner":"undefined"},"map2":{"name":"undefined","winner":"undefined"},"map3":{"name":"undefined","winner":"undefined"},"map4":{"name":"undefined","winner":"undefined"},"map5":{"name":"undefined","winner":"undefined"},"map6":{"name":"undefined","winner":"undefined"},"map7":{"name":"undefined","winner":"undefined"},"map8":{"name":"undefined","winner":"undefined"},"matchwinner":"undefined","vod":"undefined","round":"undefined"},{"tournament":"Tourn 2 playins","played":"FALSE","team1":"","team2":"","division":"","date":"","time":"","map1":{"name":"undefined","winner":"undefined"},"map2":{"name":"undefined","winner":"undefined"},"map3":{"name":"undefined","winner":"undefined"},"map4":{"name":"undefined","winner":"undefined"},"map5":{"name":"undefined","winner":"undefined"},"map6":{"name":"undefined","winner":"undefined"},"map7":{"name":"undefined","winner":"undefined"},"map8":{"name":"undefined","winner":"undefined"},"matchwinner":"undefined","vod":"undefined","round":"undefined"},{"tournament":"Tourn 2 playoffs","played":"FALSE","team1":"","team2":"","division":"","date":"","time":"","map1":{"name":"undefined","winner":"undefined"},"map2":{"name":"undefined","winner":"undefined"},"map3":{"name":"undefined","winner":"undefined"},"map4":{"name":"undefined","winner":"undefined"},"map5":{"name":"undefined","winner":"undefined"},"map6":{"name":"undefined","winner":"undefined"},"map7":{"name":"undefined","winner":"undefined"},"map8":{"name":"undefined","winner":"undefined"},"matchwinner":"undefined","vod":"undefined","round":"undefined"},{"tournament":"Tourn 2 playoffs","played":"FALSE","team1":"","team2":"","division":"","date":"","time":"","map1":{"name":"undefined","winner":"undefined"},"map2":{"name":"undefined","winner":"undefined"},"map3":{"name":"undefined","winner":"undefined"},"map4":{"name":"undefined","winner":"undefined"},"map5":{"name":"undefined","winner":"undefined"},"map6":{"name":"undefined","winner":"undefined"},"map7":{"name":"undefined","winner":"undefined"},"map8":{"name":"undefined","winner":"undefined"},"matchwinner":"undefined","vod":"undefined","round":"undefined"},{"tournament":"Tourn 2 playoffs","played":"FALSE","team1":"","team2":"","division":"","date":"","time":"","map1":{"name":"undefined","winner":"undefined"},"map2":{"name":"undefined","winner":"undefined"},"map3":{"name":"undefined","winner":"undefined"},"map4":{"name":"undefined","winner":"undefined"},"map5":{"name":"undefined","winner":"undefined"},"map6":{"name":"undefined","winner":"undefined"},"map7":{"name":"undefined","winner":"undefined"},"map8":{"name":"undefined","winner":"undefined"},"matchwinner":"undefined","vod":"undefined","round":"undefined"},{"tournament":"Tourn 2 playoffs","played":"FALSE","team1":"","team2":"","division":"","date":"","time":"","map1":{"name":"undefined","winner":"undefined"},"map2":{"name":"undefined","winner":"undefined"},"map3":{"name":"undefined","winner":"undefined"},"map4":{"name":"undefined","winner":"undefined"},"map5":{"name":"undefined","winner":"undefined"},"map6":{"name":"undefined","winner":"undefined"},"map7":{"name":"undefined","winner":"undefined"},"map8":{"name":"undefined","winner":"undefined"},"matchwinner":"undefined","vod":"undefined","round":"undefined"},{"tournament":"Tourn 2 playoffs","played":"FALSE","team1":"","team2":"","division":"","date":"","time":"","map1":{"name":"undefined","winner":"undefined"},"map2":{"name":"undefined","winner":"undefined"},"map3":{"name":"undefined","winner":"undefined"},"map4":{"name":"undefined","winner":"undefined"},"map5":{"name":"undefined","winner":"undefined"},"map6":{"name":"undefined","winner":"undefined"},"map7":{"name":"undefined","winner":"undefined"},"map8":{"name":"undefined","winner":"undefined"},"matchwinner":"undefined","vod":"undefined","round":"undefined"},{"tournament":"Tourn 2 playoffs","played":"FALSE","team1":"","team2":"","division":"","date":"","time":"","map1":{"name":"undefined","winner":"undefined"},"map2":{"name":"undefined","winner":"undefined"},"map3":{"name":"undefined","winner":"undefined"},"map4":{"name":"undefined","winner":"undefined"},"map5":{"name":"undefined","winner":"undefined"},"map6":{"name":"undefined","winner":"undefined"},"map7":{"name":"undefined","winner":"undefined"},"map8":{"name":"undefined","winner":"undefined"},"matchwinner":"undefined","vod":"undefined","round":"undefined"},{"tournament":"Tourn 2 playoffs","played":"FALSE","team1":"","team2":"","division":"","date":"","time":"","map1":{"name":"undefined","winner":"undefined"},"map2":{"name":"undefined","winner":"undefined"},"map3":{"name":"undefined","winner":"undefined"},"map4":{"name":"undefined","winner":"undefined"},"map5":{"name":"undefined","winner":"undefined"},"map6":{"name":"undefined","winner":"undefined"},"map7":{"name":"undefined","winner":"undefined"},"map8":{"name":"undefined","winner":"undefined"},"matchwinner":"undefined","vod":"undefined","round":"undefined"},{"tournament":"Tourn 3","played":"FALSE","team1":"Oceania Otters","team2":"Djibouti Shorts","division":"DIV","date":"","time":"","map1":{"name":"","winner":""},"map2":{"name":"","winner":""},"map3":{"name":"","winner":""},"map4":{"name":"","winner":""},"map5":{"name":"","winner":""},"map6":{"name":"","winner":""},"map7":{"name":"","winner":""},"map8":{"name":"","winner":""},"matchwinner":"","vod":"","round":"7"},{"tournament":"Tourn 3","played":"FALSE","team1":"Rialto Rincewinds","team2":"The Tenochitlan Tacos","division":"NDIV","date":"","time":"","map1":{"name":"","winner":""},"map2":{"name":"","winner":""},"map3":{"name":"","winner":""},"map4":{"name":"","winner":""},"map5":{"name":"","winner":""},"map6":{"name":"","winner":""},"map7":{"name":"","winner":""},"map8":{"name":"","winner":""},"matchwinner":"","vod":"","round":"7"},{"tournament":"Tourn 3","played":"FALSE","team1":"Gaming Golems","team2":"Wakanda BBQs","division":"DIV","date":"","time":"","map1":{"name":"","winner":""},"map2":{"name":"","winner":""},"map3":{"name":"","winner":""},"map4":{"name":"","winner":""},"map5":{"name":"","winner":""},"map6":{"name":"","winner":""},"map7":{"name":"","winner":""},"map8":{"name":"","winner":""},"matchwinner":"","vod":"","round":"7"},{"tournament":"Tourn 3","played":"FALSE","team1":"Bendigo Bilbies","team2":"Plymouth PMAs","division":"NDIV","date":"","time":"","map1":{"name":"","winner":""},"map2":{"name":"","winner":""},"map3":{"name":"","winner":""},"map4":{"name":"","winner":""},"map5":{"name":"","winner":""},"map6":{"name":"","winner":""},"map7":{"name":"","winner":""},"map8":{"name":"","winner":""},"matchwinner":"","vod":"","round":"7"},{"tournament":"Tourn 3","played":"FALSE","team1":"Galapagos Gremlins","team2":"London Lumberjack Slams","division":"NDIV","date":"","time":"","map1":{"name":"","winner":""},"map2":{"name":"","winner":""},"map3":{"name":"","winner":""},"map4":{"name":"","winner":""},"map5":{"name":"","winner":""},"map6":{"name":"","winner":""},"map7":{"name":"","winner":""},"map8":{"name":"","winner":""},"matchwinner":"","vod":"","round":"7"},{"tournament":"Tourn 3","played":"FALSE","team1":"Oceania Otters","team2":"Rialto Rincewinds","division":"NDIV","date":"","time":"","map1":{"name":"","winner":""},"map2":{"name":"","winner":""},"map3":{"name":"","winner":""},"map4":{"name":"","winner":""},"map5":{"name":"","winner":""},"map6":{"name":"","winner":""},"map7":{"name":"","winner":""},"map8":{"name":"","winner":""},"matchwinner":"","vod":"","round":"8"},{"tournament":"Tourn 3","played":"FALSE","team1":"Gaming Golems","team2":"Djibouti Shorts","division":"NDIV","date":"","time":"","map1":{"name":"","winner":""},"map2":{"name":"","winner":""},"map3":{"name":"","winner":""},"map4":{"name":"","winner":""},"map5":{"name":"","winner":""},"map6":{"name":"","winner":""},"map7":{"name":"","winner":""},"map8":{"name":"","winner":""},"matchwinner":"","vod":"","round":"8"},{"tournament":"Tourn 3","played":"FALSE","team1":"Bendigo Bilbies","team2":"The Tenochitlan Tacos","division":"NDIV","date":"","time":"","map1":{"name":"","winner":""},"map2":{"name":"","winner":""},"map3":{"name":"","winner":""},"map4":{"name":"","winner":""},"map5":{"name":"","winner":""},"map6":{"name":"","winner":""},"map7":{"name":"","winner":""},"map8":{"name":"","winner":""},"matchwinner":"","vod":"","round":"8"},{"tournament":"Tourn 3","played":"FALSE","team1":"Galapagos Gremlins","team2":"Wakanda BBQs","division":"DIV","date":"","time":"","map1":{"name":"","winner":""},"map2":{"name":"","winner":""},"map3":{"name":"","winner":""},"map4":{"name":"","winner":""},"map5":{"name":"","winner":""},"map6":{"name":"","winner":""},"map7":{"name":"","winner":""},"map8":{"name":"","winner":""},"matchwinner":"","vod":"","round":"8"},{"tournament":"Tourn 3","played":"FALSE","team1":"London Lumberjack Slams","team2":"Plymouth PMAs","division":"DIV","date":"","time":"","map1":{"name":"","winner":""},"map2":{"name":"","winner":""},"map3":{"name":"","winner":""},"map4":{"name":"","winner":""},"map5":{"name":"","winner":""},"map6":{"name":"","winner":""},"map7":{"name":"","winner":""},"map8":{"name":"","winner":""},"matchwinner":"","vod":"","round":"8"},{"tournament":"Tourn 3","played":"FALSE","team1":"Oceania Otters","team2":"Gaming Golems","division":"NDIV","date":"","time":"","map1":{"name":"","winner":""},"map2":{"name":"","winner":""},"map3":{"name":"","winner":""},"map4":{"name":"","winner":""},"map5":{"name":"","winner":""},"map6":{"name":"","winner":""},"map7":{"name":"","winner":""},"map8":{"name":"","winner":""},"matchwinner":"","vod":"","round":"9"},{"tournament":"Tourn 3","played":"FALSE","team1":"Bendigo Bilbies","team2":"Rialto Rincewinds","division":"DIV","date":"","time":"","map1":{"name":"","winner":""},"map2":{"name":"","winner":""},"map3":{"name":"","winner":""},"map4":{"name":"","winner":""},"map5":{"name":"","winner":""},"map6":{"name":"","winner":""},"map7":{"name":"","winner":""},"map8":{"name":"","winner":""},"matchwinner":"","vod":"","round":"9"},{"tournament":"Tourn 3","played":"FALSE","team1":"Galapagos Gremlins","team2":"Djibouti Shorts","division":"NDIV","date":"","time":"","map1":{"name":"","winner":""},"map2":{"name":"","winner":""},"map3":{"name":"","winner":""},"map4":{"name":"","winner":""},"map5":{"name":"","winner":""},"map6":{"name":"","winner":""},"map7":{"name":"","winner":""},"map8":{"name":"","winner":""},"matchwinner":"","vod":"","round":"9"},{"tournament":"Tourn 3","played":"FALSE","team1":"London Lumberjack Slams","team2":"The Tenochitlan Tacos","division":"DIV","date":"","time":"","map1":{"name":"","winner":""},"map2":{"name":"","winner":""},"map3":{"name":"","winner":""},"map4":{"name":"","winner":""},"map5":{"name":"","winner":""},"map6":{"name":"","winner":""},"map7":{"name":"","winner":""},"map8":{"name":"","winner":""},"matchwinner":"","vod":"","round":"9"},{"tournament":"Tourn 3","played":"FALSE","team1":"Plymouth PMAs","team2":"Wakanda BBQs","division":"NDIV","date":"","time":"","map1":{"name":"","winner":""},"map2":{"name":"","winner":""},"map3":{"name":"","winner":""},"map4":{"name":"","winner":""},"map5":{"name":"","winner":""},"map6":{"name":"","winner":""},"map7":{"name":"","winner":""},"map8":{"name":"","winner":""},"matchwinner":"","vod":"","round":"9"},{"tournament":"Tourn 3 playins","played":"FALSE","team1":"","team2":"","division":"","date":"","time":"","map1":{"name":"undefined","winner":"undefined"},"map2":{"name":"undefined","winner":"undefined"},"map3":{"name":"undefined","winner":"undefined"},"map4":{"name":"undefined","winner":"undefined"},"map5":{"name":"undefined","winner":"undefined"},"map6":{"name":"undefined","winner":"undefined"},"map7":{"name":"undefined","winner":"undefined"},"map8":{"name":"undefined","winner":"undefined"},"matchwinner":"undefined","vod":"undefined","round":"undefined"},{"tournament":"Tourn 3 playins","played":"FALSE","team1":"","team2":"","division":"","date":"","time":"","map1":{"name":"undefined","winner":"undefined"},"map2":{"name":"undefined","winner":"undefined"},"map3":{"name":"undefined","winner":"undefined"},"map4":{"name":"undefined","winner":"undefined"},"map5":{"name":"undefined","winner":"undefined"},"map6":{"name":"undefined","winner":"undefined"},"map7":{"name":"undefined","winner":"undefined"},"map8":{"name":"undefined","winner":"undefined"},"matchwinner":"undefined","vod":"undefined","round":"undefined"},{"tournament":"Tourn 3 playins","played":"FALSE","team1":"","team2":"","division":"","date":"","time":"","map1":{"name":"undefined","winner":"undefined"},"map2":{"name":"undefined","winner":"undefined"},"map3":{"name":"undefined","winner":"undefined"},"map4":{"name":"undefined","winner":"undefined"},"map5":{"name":"undefined","winner":"undefined"},"map6":{"name":"undefined","winner":"undefined"},"map7":{"name":"undefined","winner":"undefined"},"map8":{"name":"undefined","winner":"undefined"},"matchwinner":"undefined","vod":"undefined","round":"undefined"},{"tournament":"Tourn 3 playoffs","played":"FALSE","team1":"","team2":"","division":"","date":"","time":"","map1":{"name":"undefined","winner":"undefined"},"map2":{"name":"undefined","winner":"undefined"},"map3":{"name":"undefined","winner":"undefined"},"map4":{"name":"undefined","winner":"undefined"},"map5":{"name":"undefined","winner":"undefined"},"map6":{"name":"undefined","winner":"undefined"},"map7":{"name":"undefined","winner":"undefined"},"map8":{"name":"undefined","winner":"undefined"},"matchwinner":"undefined","vod":"undefined","round":"undefined"},{"tournament":"Tourn 3 playoffs","played":"FALSE","team1":"","team2":"","division":"","date":"","time":"","map1":{"name":"undefined","winner":"undefined"},"map2":{"name":"undefined","winner":"undefined"},"map3":{"name":"undefined","winner":"undefined"},"map4":{"name":"undefined","winner":"undefined"},"map5":{"name":"undefined","winner":"undefined"},"map6":{"name":"undefined","winner":"undefined"},"map7":{"name":"undefined","winner":"undefined"},"map8":{"name":"undefined","winner":"undefined"},"matchwinner":"undefined","vod":"undefined","round":"undefined"},{"tournament":"Tourn 3 playoffs","played":"FALSE","team1":"","team2":"","division":"","date":"","time":"","map1":{"name":"undefined","winner":"undefined"},"map2":{"name":"undefined","winner":"undefined"},"map3":{"name":"undefined","winner":"undefined"},"map4":{"name":"undefined","winner":"undefined"},"map5":{"name":"undefined","winner":"undefined"},"map6":{"name":"undefined","winner":"undefined"},"map7":{"name":"undefined","winner":"undefined"},"map8":{"name":"undefined","winner":"undefined"},"matchwinner":"undefined","vod":"undefined","round":"undefined"},{"tournament":"Tourn 3 playoffs","played":"FALSE","team1":"","team2":"","division":"","date":"","time":"","map1":{"name":"undefined","winner":"undefined"},"map2":{"name":"undefined","winner":"undefined"},"map3":{"name":"undefined","winner":"undefined"},"map4":{"name":"undefined","winner":"undefined"},"map5":{"name":"undefined","winner":"undefined"},"map6":{"name":"undefined","winner":"undefined"},"map7":{"name":"undefined","winner":"undefined"},"map8":{"name":"undefined","winner":"undefined"},"matchwinner":"undefined","vod":"undefined","round":"undefined"},{"tournament":"Tourn 3 playoffs","played":"FALSE","team1":"","team2":"","division":"","date":"","time":"","map1":{"name":"undefined","winner":"undefined"},"map2":{"name":"undefined","winner":"undefined"},"map3":{"name":"undefined","winner":"undefined"},"map4":{"name":"undefined","winner":"undefined"},"map5":{"name":"undefined","winner":"undefined"},"map6":{"name":"undefined","winner":"undefined"},"map7":{"name":"undefined","winner":"undefined"},"map8":{"name":"undefined","winner":"undefined"},"matchwinner":"undefined","vod":"undefined","round":"undefined"},{"tournament":"Tourn 3 playoffs","played":"FALSE","team1":"","team2":"","division":"","date":"","time":"","map1":{"name":"undefined","winner":"undefined"},"map2":{"name":"undefined","winner":"undefined"},"map3":{"name":"undefined","winner":"undefined"},"map4":{"name":"undefined","winner":"undefined"},"map5":{"name":"undefined","winner":"undefined"},"map6":{"name":"undefined","winner":"undefined"},"map7":{"name":"undefined","winner":"undefined"},"map8":{"name":"undefined","winner":"undefined"},"matchwinner":"undefined","vod":"undefined","round":"undefined"},{"tournament":"Tourn 3 playoffs","played":"FALSE","team1":"","team2":"","division":"","date":"","time":"","map1":{"name":"undefined","winner":"undefined"},"map2":{"name":"undefined","winner":"undefined"},"map3":{"name":"undefined","winner":"undefined"},"map4":{"name":"undefined","winner":"undefined"},"map5":{"name":"undefined","winner":"undefined"},"map6":{"name":"undefined","winner":"undefined"},"map7":{"name":"undefined","winner":"undefined"},"map8":{"name":"undefined","winner":"undefined"},"matchwinner":"undefined","vod":"undefined","round":"undefined"},{"tournament":"League playins","played":"FALSE","team1":"","team2":"","division":"","date":"","time":"","map1":{"name":"undefined","winner":"undefined"},"map2":{"name":"undefined","winner":"undefined"},"map3":{"name":"undefined","winner":"undefined"},"map4":{"name":"undefined","winner":"undefined"},"map5":{"name":"undefined","winner":"undefined"},"map6":{"name":"undefined","winner":"undefined"},"map7":{"name":"undefined","winner":"undefined"},"map8":{"name":"undefined","winner":"undefined"},"matchwinner":"undefined","vod":"undefined","round":"undefined"},{"tournament":"League playins","played":"FALSE","team1":"","team2":"","division":"","date":"","time":"","map1":{"name":"undefined","winner":"undefined"},"map2":{"name":"undefined","winner":"undefined"},"map3":{"name":"undefined","winner":"undefined"},"map4":{"name":"undefined","winner":"undefined"},"map5":{"name":"undefined","winner":"undefined"},"map6":{"name":"undefined","winner":"undefined"},"map7":{"name":"undefined","winner":"undefined"},"map8":{"name":"undefined","winner":"undefined"},"matchwinner":"undefined","vod":"undefined","round":"undefined"},{"tournament":"League playins","played":"FALSE","team1":"","team2":"","division":"","date":"","time":"","map1":{"name":"undefined","winner":"undefined"},"map2":{"name":"undefined","winner":"undefined"},"map3":{"name":"undefined","winner":"undefined"},"map4":{"name":"undefined","winner":"undefined"},"map5":{"name":"undefined","winner":"undefined"},"map6":{"name":"undefined","winner":"undefined"},"map7":{"name":"undefined","winner":"undefined"},"map8":{"name":"undefined","winner":"undefined"},"matchwinner":"undefined","vod":"undefined","round":"undefined"},{"tournament":"League playoffs","played":"FALSE","team1":"","team2":"","division":"","date":"","time":"","map1":{"name":"undefined","winner":"undefined"},"map2":{"name":"undefined","winner":"undefined"},"map3":{"name":"undefined","winner":"undefined"},"map4":{"name":"undefined","winner":"undefined"},"map5":{"name":"undefined","winner":"undefined"},"map6":{"name":"undefined","winner":"undefined"},"map7":{"name":"undefined","winner":"undefined"},"map8":{"name":"undefined","winner":"undefined"},"matchwinner":"undefined","vod":"undefined","round":"undefined"},{"tournament":"League playoffs","played":"FALSE","team1":"","team2":"","division":"","date":"","time":"","map1":{"name":"undefined","winner":"undefined"},"map2":{"name":"undefined","winner":"undefined"},"map3":{"name":"undefined","winner":"undefined"},"map4":{"name":"undefined","winner":"undefined"},"map5":{"name":"undefined","winner":"undefined"},"map6":{"name":"undefined","winner":"undefined"},"map7":{"name":"undefined","winner":"undefined"},"map8":{"name":"undefined","winner":"undefined"},"matchwinner":"undefined","vod":"undefined","round":"undefined"},{"tournament":"League playoffs","played":"FALSE","team1":"","team2":"","division":"","date":"","time":"","map1":{"name":"undefined","winner":"undefined"},"map2":{"name":"undefined","winner":"undefined"},"map3":{"name":"undefined","winner":"undefined"},"map4":{"name":"undefined","winner":"undefined"},"map5":{"name":"undefined","winner":"undefined"},"map6":{"name":"undefined","winner":"undefined"},"map7":{"name":"undefined","winner":"undefined"},"map8":{"name":"undefined","winner":"undefined"},"matchwinner":"undefined","vod":"undefined","round":"undefined"},{"tournament":"League playoffs","played":"FALSE","team1":"","team2":"","division":"","date":"","time":"","map1":{"name":"undefined","winner":"undefined"},"map2":{"name":"undefined","winner":"undefined"},"map3":{"name":"undefined","winner":"undefined"},"map4":{"name":"undefined","winner":"undefined"},"map5":{"name":"undefined","winner":"undefined"},"map6":{"name":"undefined","winner":"undefined"},"map7":{"name":"undefined","winner":"undefined"},"map8":{"name":"undefined","winner":"undefined"},"matchwinner":"undefined","vod":"undefined","round":"undefined"},{"tournament":"League playoffs","played":"FALSE","team1":"","team2":"","division":"","date":"","time":"","map1":{"name":"undefined","winner":"undefined"},"map2":{"name":"undefined","winner":"undefined"},"map3":{"name":"undefined","winner":"undefined"},"map4":{"name":"undefined","winner":"undefined"},"map5":{"name":"undefined","winner":"undefined"},"map6":{"name":"undefined","winner":"undefined"},"map7":{"name":"undefined","winner":"undefined"},"map8":{"name":"undefined","winner":"undefined"},"matchwinner":"undefined","vod":"undefined","round":"undefined"},{"tournament":"League playoffs","played":"FALSE","team1":"","team2":"","division":"","date":"","time":"","map1":{"name":"undefined","winner":"undefined"},"map2":{"name":"undefined","winner":"undefined"},"map3":{"name":"undefined","winner":"undefined"},"map4":{"name":"undefined","winner":"undefined"},"map5":{"name":"undefined","winner":"undefined"},"map6":{"name":"undefined","winner":"undefined"},"map7":{"name":"undefined","winner":"undefined"},"map8":{"name":"undefined","winner":"undefined"},"matchwinner":"undefined","vod":"undefined","round":"undefined"},{"tournament":"League playoffs","played":"FALSE","team1":"","team2":"","division":"","date":"","time":"","map1":{"name":"undefined","winner":"undefined"},"map2":{"name":"undefined","winner":"undefined"},"map3":{"name":"undefined","winner":"undefined"},"map4":{"name":"undefined","winner":"undefined"},"map5":{"name":"undefined","winner":"undefined"},"map6":{"name":"undefined","winner":"undefined"},"map7":{"name":"undefined","winner":"undefined"},"map8":{"name":"undefined","winner":"undefined"},"matchwinner":"undefined","vod":"undefined","round":"undefined"},{"tournament":"","played":"FALSE","team1":"","team2":"","division":"","date":"","time":"","map1":{"name":"undefined","winner":"undefined"},"map2":{"name":"undefined","winner":"undefined"},"map3":{"name":"undefined","winner":"undefined"},"map4":{"name":"undefined","winner":"undefined"},"map5":{"name":"undefined","winner":"undefined"},"map6":{"name":"undefined","winner":"undefined"},"map7":{"name":"undefined","winner":"undefined"},"map8":{"name":"undefined","winner":"undefined"},"matchwinner":"undefined","vod":"undefined","round":"undefined"},{"tournament":"","played":"FALSE","team1":"","team2":"","division":"","date":"","time":"","map1":{"name":"undefined","winner":"undefined"},"map2":{"name":"undefined","winner":"undefined"},"map3":{"name":"undefined","winner":"undefined"},"map4":{"name":"undefined","winner":"undefined"},"map5":{"name":"undefined","winner":"undefined"},"map6":{"name":"undefined","winner":"undefined"},"map7":{"name":"undefined","winner":"undefined"},"map8":{"name":"undefined","winner":"undefined"},"matchwinner":"undefined","vod":"undefined","round":"undefined"},{"tournament":"","played":"FALSE","team1":"","team2":"","division":"","date":"","time":"","map1":{"name":"undefined","winner":"undefined"},"map2":{"name":"undefined","winner":"undefined"},"map3":{"name":"undefined","winner":"undefined"},"map4":{"name":"undefined","winner":"undefined"},"map5":{"name":"undefined","winner":"undefined"},"map6":{"name":"undefined","winner":"undefined"},"map7":{"name":"undefined","winner":"undefined"},"map8":{"name":"undefined","winner":"undefined"},"matchwinner":"undefined","vod":"undefined","round":"undefined"},{"tournament":"","played":"FALSE","team1":"","team2":"","division":"","date":"","time":"","map1":{"name":"undefined","winner":"undefined"},"map2":{"name":"undefined","winner":"undefined"},"map3":{"name":"undefined","winner":"undefined"},"map4":{"name":"undefined","winner":"undefined"},"map5":{"name":"undefined","winner":"undefined"},"map6":{"name":"undefined","winner":"undefined"},"map7":{"name":"undefined","winner":"undefined"},"map8":{"name":"undefined","winner":"undefined"},"matchwinner":"undefined","vod":"undefined","round":"undefined"},{"tournament":"","played":"FALSE","team1":"","team2":"","division":"","date":"","time":"","map1":{"name":"undefined","winner":"undefined"},"map2":{"name":"undefined","winner":"undefined"},"map3":{"name":"undefined","winner":"undefined"},"map4":{"name":"undefined","winner":"undefined"},"map5":{"name":"undefined","winner":"undefined"},"map6":{"name":"undefined","winner":"undefined"},"map7":{"name":"undefined","winner":"undefined"},"map8":{"name":"undefined","winner":"undefined"},"matchwinner":"undefined","vod":"undefined","round":"undefined"},{"tournament":"","played":"FALSE","team1":"","team2":"","division":"","date":"","time":"","map1":{"name":"undefined","winner":"undefined"},"map2":{"name":"undefined","winner":"undefined"},"map3":{"name":"undefined","winner":"undefined"},"map4":{"name":"undefined","winner":"undefined"},"map5":{"name":"undefined","winner":"undefined"},"map6":{"name":"undefined","winner":"undefined"},"map7":{"name":"undefined","winner":"undefined"},"map8":{"name":"undefined","winner":"undefined"},"matchwinner":"undefined","vod":"undefined","round":"undefined"},{"tournament":"","played":"FALSE","team1":"","team2":"","division":"","date":"","time":"","map1":{"name":"undefined","winner":"undefined"},"map2":{"name":"undefined","winner":"undefined"},"map3":{"name":"undefined","winner":"undefined"},"map4":{"name":"undefined","winner":"undefined"},"map5":{"name":"undefined","winner":"undefined"},"map6":{"name":"undefined","winner":"undefined"},"map7":{"name":"undefined","winner":"undefined"},"map8":{"name":"undefined","winner":"undefined"},"matchwinner":"undefined","vod":"undefined","round":"undefined"},{"tournament":"","played":"FALSE","team1":"","team2":"","division":"","date":"","time":"","map1":{"name":"undefined","winner":"undefined"},"map2":{"name":"undefined","winner":"undefined"},"map3":{"name":"undefined","winner":"undefined"},"map4":{"name":"undefined","winner":"undefined"},"map5":{"name":"undefined","winner":"undefined"},"map6":{"name":"undefined","winner":"undefined"},"map7":{"name":"undefined","winner":"undefined"},"map8":{"name":"undefined","winner":"undefined"},"matchwinner":"undefined","vod":"undefined","round":"undefined"},{"tournament":"","played":"FALSE","team1":"","team2":"","division":"","date":"","time":"","map1":{"name":"undefined","winner":"undefined"},"map2":{"name":"undefined","winner":"undefined"},"map3":{"name":"undefined","winner":"undefined"},"map4":{"name":"undefined","winner":"undefined"},"map5":{"name":"undefined","winner":"undefined"},"map6":{"name":"undefined","winner":"undefined"},"map7":{"name":"undefined","winner":"undefined"},"map8":{"name":"undefined","winner":"undefined"},"matchwinner":"undefined","vod":"undefined","round":"undefined"},{"tournament":"","played":"FALSE","team1":"","team2":"","division":"","date":"","time":"","map1":{"name":"undefined","winner":"undefined"},"map2":{"name":"undefined","winner":"undefined"},"map3":{"name":"undefined","winner":"undefined"},"map4":{"name":"undefined","winner":"undefined"},"map5":{"name":"undefined","winner":"undefined"},"map6":{"name":"undefined","winner":"undefined"},"map7":{"name":"undefined","winner":"undefined"},"map8":{"name":"undefined","winner":"undefined"},"matchwinner":"undefined","vod":"undefined","round":"undefined"},{"tournament":"","played":"FALSE","team1":"","team2":"","division":"","date":"","time":"","map1":{"name":"undefined","winner":"undefined"},"map2":{"name":"undefined","winner":"undefined"},"map3":{"name":"undefined","winner":"undefined"},"map4":{"name":"undefined","winner":"undefined"},"map5":{"name":"undefined","winner":"undefined"},"map6":{"name":"undefined","winner":"undefined"},"map7":{"name":"undefined","winner":"undefined"},"map8":{"name":"undefined","winner":"undefined"},"matchwinner":"undefined","vod":"undefined","round":"undefined"},{"tournament":"","played":"FALSE","team1":"","team2":"","division":"","date":"","time":"","map1":{"name":"undefined","winner":"undefined"},"map2":{"name":"undefined","winner":"undefined"},"map3":{"name":"undefined","winner":"undefined"},"map4":{"name":"undefined","winner":"undefined"},"map5":{"name":"undefined","winner":"undefined"},"map6":{"name":"undefined","winner":"undefined"},"map7":{"name":"undefined","winner":"undefined"},"map8":{"name":"undefined","winner":"undefined"},"matchwinner":"undefined","vod":"undefined","round":"undefined"},{"tournament":"","played":"FALSE","team1":"","team2":"","division":"","date":"","time":"","map1":{"name":"undefined","winner":"undefined"},"map2":{"name":"undefined","winner":"undefined"},"map3":{"name":"undefined","winner":"undefined"},"map4":{"name":"undefined","winner":"undefined"},"map5":{"name":"undefined","winner":"undefined"},"map6":{"name":"undefined","winner":"undefined"},"map7":{"name":"undefined","winner":"undefined"},"map8":{"name":"undefined","winner":"undefined"},"matchwinner":"undefined","vod":"undefined","round":"undefined"}]}